dramatiq_crontab/__init__.py
dramatiq_crontab/_version.py
dramatiq_crontab/conf.py
dramatiq_crontab/tasks.py
dramatiq_crontab/utils.py
dramatiq_crontab/management/__init__.py
dramatiq_crontab/management/commands/__init__.py
dramatiq_crontab/management/commands/crontab.py
dramatiq_crontab-1.0.12.dist-info/licenses/LICENSE
dramatiq_crontab-1.0.12.dist-info/WHEEL
dramatiq_crontab-1.0.12.dist-info/METADATA
dramatiq_crontab-1.0.12.dist-info/RECORD
