Metadata-Version: 2.4
Name: dramatiq-crontab
Version: 1.0.12
Summary: Cron style scheduler for asynchronous Dramatiq tasks in Django.
Keywords: Django,Dramatiq,tasks,scheduler
Author-email: Rust Saiargaliev <fly.amureki@gmail.com>, Johannes Maron <johannes@maron.family>, Mostafa Mohamed <mostafa.anm91@gmail.com>, Jacqueline Kraus <jacquelinekraus1992@gmail.com>
Requires-Python: >=3.9
Classifier: Development Status :: 5 - Production/Stable
Classifier: Programming Language :: Python
Classifier: Environment :: Web Environment
Classifier: License :: OSI Approved :: BSD License
Classifier: Intended Audience :: Developers
Classifier: Operating System :: OS Independent
Classifier: Topic :: Communications :: Email
Classifier: Topic :: Text Processing :: Markup :: Markdown
Classifier: Topic :: Software Development
Classifier: Programming Language :: Python
Classifier: Programming Language :: Python :: 3
Classifier: Programming Language :: Python :: 3 :: Only
Classifier: Programming Language :: Python :: 3.9
Classifier: Programming Language :: Python :: 3.10
Classifier: Programming Language :: Python :: 3.11
Classifier: Programming Language :: Python :: 3.12
Classifier: Programming Language :: Python :: 3.13
Classifier: Framework :: Django
Classifier: Framework :: Django :: 4.2
Classifier: Framework :: Django :: 5.1
Classifier: Framework :: Django :: 5.2
License-File: LICENSE
Requires-Dist: dramatiq
Requires-Dist: apscheduler
Requires-Dist: django
Requires-Dist: black==25.1.0 ; extra == "lint"
Requires-Dist: ruff==0.12.7 ; extra == "lint"
Requires-Dist: redis ; extra == "redis"
Requires-Dist: sentry-sdk ; extra == "sentry"
Requires-Dist: pytest ; extra == "test"
Requires-Dist: pytest-cov ; extra == "test"
Requires-Dist: pytest-django ; extra == "test"
Requires-Dist: dramatiq ; extra == "test"
Requires-Dist: backports.zoneinfo ; extra == "test" and (python_version<'3.9')
Project-URL: Changelog, https://github.com/voiio/dramatiq-crontab/releases
Project-URL: Project-URL, https://github.com/voiio/dramatiq-crontab
Provides-Extra: lint
Provides-Extra: redis
Provides-Extra: sentry
Provides-Extra: test
